{"nodes": [{"id": "d_med_broker_app_backend_src_modules_admin_trainingdata_service_js", "label": "trainingData.service.js", "file_type": "code", "source_file": "D:\\med-broker-app\\backend\\src\\modules\\admin\\trainingData.service.js", "source_location": "L1"}, {"id": "trainingdata_service_exportdemandtrainingdata", "label": "exportDemandTrainingData()", "file_type": "code", "source_file": "D:\\med-broker-app\\backend\\src\\modules\\admin\\trainingData.service.js", "source_location": "L8"}], "edges": [{"source": "d_med_broker_app_backend_src_modules_admin_trainingdata_service_js", "target": "trainingdata_service_exportdemandtrainingdata", "relation": "contains", "confidence": "EXTRACTED", "source_file": "D:\\med-broker-app\\backend\\src\\modules\\admin\\trainingData.service.js", "source_location": "L8", "weight": 1.0}], "raw_calls": [{"caller_nid": "trainingdata_service_exportdemandtrainingdata", "callee": "setMonth", "source_file": "D:\\med-broker-app\\backend\\src\\modules\\admin\\trainingData.service.js", "source_location": "L11"}, {"caller_nid": "trainingdata_service_exportdemandtrainingdata", "callee": "getMonth", "source_file": "D:\\med-broker-app\\backend\\src\\modules\\admin\\trainingData.service.js", "source_location": "L11"}, {"caller_nid": "trainingdata_service_exportdemandtrainingdata", "callee": "findMany", "source_file": "D:\\med-broker-app\\backend\\src\\modules\\admin\\trainingData.service.js", "source_location": "L14"}, {"caller_nid": "trainingdata_service_exportdemandtrainingdata", "callee": "findMany", "source_file": "D:\\med-broker-app\\backend\\src\\modules\\admin\\trainingData.service.js", "source_location": "L37"}, {"caller_nid": "trainingdata_service_exportdemandtrainingdata", "callee": "findMany", "source_file": "D:\\med-broker-app\\backend\\src\\modules\\admin\\trainingData.service.js", "source_location": "L51"}, {"caller_nid": "trainingdata_service_exportdemandtrainingdata", "callee": "forEach", "source_file": "D:\\med-broker-app\\backend\\src\\modules\\admin\\trainingData.service.js", "source_location": "L62"}, {"caller_nid": "trainingdata_service_exportdemandtrainingdata", "callee": "forEach", "source_file": "D:\\med-broker-app\\backend\\src\\modules\\admin\\trainingData.service.js", "source_location": "L75"}, {"caller_nid": "trainingdata_service_exportdemandtrainingdata", "callee": "forEach", "source_file": "D:\\med-broker-app\\backend\\src\\modules\\admin\\trainingData.service.js", "source_location": "L79"}, {"caller_nid": "trainingdata_service_exportdemandtrainingdata", "callee": "forEach", "source_file": "D:\\med-broker-app\\backend\\src\\modules\\admin\\trainingData.service.js", "source_location": "L90"}, {"caller_nid": "trainingdata_service_exportdemandtrainingdata", "callee": "forEach", "source_file": "D:\\med-broker-app\\backend\\src\\modules\\admin\\trainingData.service.js", "source_location": "L102"}, {"caller_nid": "trainingdata_service_exportdemandtrainingdata", "callee": "push", "source_file": "D:\\med-broker-app\\backend\\src\\modules\\admin\\trainingData.service.js", "source_location": "L111"}, {"caller_nid": "trainingdata_service_exportdemandtrainingdata", "callee": "getFullYear", "source_file": "D:\\med-broker-app\\backend\\src\\modules\\admin\\trainingData.service.js", "source_location": "L111"}, {"caller_nid": "trainingdata_service_exportdemandtrainingdata", "callee": "padStart", "source_file": "D:\\med-broker-app\\backend\\src\\modules\\admin\\trainingData.service.js", "source_location": "L111"}, {"caller_nid": "trainingdata_service_exportdemandtrainingdata", "callee": "String", "source_file": "D:\\med-broker-app\\backend\\src\\modules\\admin\\trainingData.service.js", "source_location": "L111"}, {"caller_nid": "trainingdata_service_exportdemandtrainingdata", "callee": "getMonth", "source_file": "D:\\med-broker-app\\backend\\src\\modules\\admin\\trainingData.service.js", "source_location": "L111"}, {"caller_nid": "trainingdata_service_exportdemandtrainingdata", "callee": "setMonth", "source_file": "D:\\med-broker-app\\backend\\src\\modules\\admin\\trainingData.service.js", "source_location": "L112"}, {"caller_nid": "trainingdata_service_exportdemandtrainingdata", "callee": "getMonth", "source_file": "D:\\med-broker-app\\backend\\src\\modules\\admin\\trainingData.service.js", "source_location": "L112"}, {"caller_nid": "trainingdata_service_exportdemandtrainingdata", "callee": "forEach", "source_file": "D:\\med-broker-app\\backend\\src\\modules\\admin\\trainingData.service.js", "source_location": "L119"}, {"caller_nid": "trainingdata_service_exportdemandtrainingdata", "callee": "toISOString", "source_file": "D:\\med-broker-app\\backend\\src\\modules\\admin\\trainingData.service.js", "source_location": "L157"}]}